pyscpi/__init__.py
pyscpi/scpi.py
pyscpi/usbtmc.py
pyscpi/keysight/__init__.py
pyscpi/keysight/osc.py
pyscpi-0.5.2.dist-info/METADATA
pyscpi-0.5.2.dist-info/WHEEL
pyscpi-0.5.2.dist-info/licenses/LICENSE
pyscpi-0.5.2.dist-info/RECORD
