Metadata-Version: 2.1
Name: pyscpi
Version: 0.5.2
Summary: A Python library for communicating with SCPI devices and a helper library for communicating with the Keysight's Smart Bench Essentials
Project-URL: Homepage, https://github.com/danchitnis/pyscpi/
Project-URL: Bug Tracker, https://github.com/danchitnis/pyscpi/issues
Author-email: Danial Chitnis <d.chitnis@ed.ac.uk>
License-File: LICENSE
Classifier: License :: OSI Approved :: MIT License
Classifier: Operating System :: OS Independent
Classifier: Programming Language :: Python :: 3
Requires-Python: >=3.7
